LICENSE
README.md
pyproject.toml
toxicbuild_core.egg-info/PKG-INFO
toxicbuild_core.egg-info/SOURCES.txt
toxicbuild_core.egg-info/dependency_links.txt
toxicbuild_core.egg-info/requires.txt
toxicbuild_core.egg-info/top_level.txt
toxiccore/__init__.py
toxiccore/build_config.py
toxiccore/client.py
toxiccore/cmd.py
toxiccore/conf.py
toxiccore/exceptions.py
toxiccore/mail.py
toxiccore/plugins.py
toxiccore/protocol.py
toxiccore/requests.py
toxiccore/server.py
toxiccore/shell.py
toxiccore/socks.py
toxiccore/utils.py
toxiccore/vcs.py